pre_commit_run_hook_entry.py
pre_commit_run_hook_entry-1.0.0a3.dist-info/entry_points.txt
pre_commit_run_hook_entry-1.0.0a3.dist-info/LICENSE
pre_commit_run_hook_entry-1.0.0a3.dist-info/WHEEL
pre_commit_run_hook_entry-1.0.0a3.dist-info/METADATA
pre_commit_run_hook_entry-1.0.0a3.dist-info/RECORD
