Metadata-Version: 2.1
Name: pre-commit-run-hook-entry
Version: 1.0.0a3
Summary: Run pre-commit hook entry. Allow to run pre-commit hooks for text editor formatting / linting needs
Home-page: https://igordavydenko.com/projects/#pre-commit-run-hook-entry
License: BSD-3-Clause
Keywords: pre-commit,pre-commit hook,vscode,sublime-text3
Author: Igor Davydenko
Author-email: iam@igordavydenko.com
Requires-Python: >=3.7,<4.0
Classifier: Development Status :: 3 - Alpha
Classifier: Environment :: Plugins
Classifier: Intended Audience :: Developers
Classifier: License :: OSI Approved :: BSD License
Classifier: Operating System :: OS Independent
Classifier: Programming Language :: Python :: 3
Classifier: Programming Language :: Python :: 3 :: Only
Classifier: Programming Language :: Python :: 3.7
Classifier: Programming Language :: Python :: 3.8
Classifier: Topic :: Utilities
Classifier: Typing :: Typed
Requires-Dist: pre-commit (>=2.7.1,<3.0.0)
Project-URL: Bug Tracker, https://github.com/playpauseandstop/pre-commit-run-hook-entry/issues
Project-URL: Repository, https://github.com/playpauseandstop/pre-commit-run-hook-entry
